MANIFEST.in
README.txt
setup.py
Products/__init__.py
Products.AROfficeTransforms.egg-info/PKG-INFO
Products.AROfficeTransforms.egg-info/SOURCES.txt
Products.AROfficeTransforms.egg-info/dependency_links.txt
Products.AROfficeTransforms.egg-info/entry_points.txt
Products.AROfficeTransforms.egg-info/namespace_packages.txt
Products.AROfficeTransforms.egg-info/not-zip-safe
Products.AROfficeTransforms.egg-info/requires.txt
Products.AROfficeTransforms.egg-info/top_level.txt
Products/AROfficeTransforms/TODO
Products/AROfficeTransforms/__init__.py
Products/AROfficeTransforms/config.py
Products/AROfficeTransforms/configure.zcml
Products/AROfficeTransforms/setuphandlers.py
Products/AROfficeTransforms/Extensions/Install.py
Products/AROfficeTransforms/Extensions/__init__.py
Products/AROfficeTransforms/profiles/default/Products.AROfficeTransforms-tranforms.txt
Products/AROfficeTransforms/profiles/default/import_steps.xml
Products/AROfficeTransforms/profiles/default/metadata.xml
Products/AROfficeTransforms/tests/__init__.py
Products/AROfficeTransforms/tests/framework.py
Products/AROfficeTransforms/tests/runalltests.py
Products/AROfficeTransforms/tests/runtests.sh.example
Products/AROfficeTransforms/tests/test_doctests.py
Products/AROfficeTransforms/tests/test_engine.py
Products/AROfficeTransforms/tests/test_graph.py
Products/AROfficeTransforms/tests/test_transforms.py
Products/AROfficeTransforms/tests/utils.py
Products/AROfficeTransforms/tests/word.py
Products/AROfficeTransforms/tests/input/demo1.pdf
Products/AROfficeTransforms/tests/input/test_doc.doc
Products/AROfficeTransforms/tests/input/test_odp.odp
Products/AROfficeTransforms/tests/input/test_ods.ods
Products/AROfficeTransforms/tests/input/test_odt.odt
Products/AROfficeTransforms/tests/input/test_ppt.ppt
Products/AROfficeTransforms/tests/input/test_sxc.sxc
Products/AROfficeTransforms/tests/input/test_sxi.sxi
Products/AROfficeTransforms/tests/input/test_sxw.sxw
Products/AROfficeTransforms/tests/input/unknown.pdf
Products/AROfficeTransforms/tests/output/test_doc.html
Products/AROfficeTransforms/tests/output/test_doc.txt
Products/AROfficeTransforms/tests/output/test_odp.html
Products/AROfficeTransforms/tests/output/test_ods.html
Products/AROfficeTransforms/tests/output/test_odt.html
Products/AROfficeTransforms/tests/output/test_ppt.html
Products/AROfficeTransforms/tests/output/test_sxc.html
