Metadata-Version: 1.0
Name: Products.AROfficeTransforms
Version: 0.11.0
Summary: Plone module to add conversion from office format to HTML in portal_transforms tool
Home-page: http://svn.plone.org/svn/collective/Products.AROfficeTransforms/
Author: atReal
Author-email: contact@atreal.fr
License: GPL
Keywords: plone transforms
Platform: UNKNOWN
Classifier: Framework :: Plone
Classifier: Programming Language :: Python
